moarcframework/__init__.py
moarcframework/models.py
moarcframework/urls.py
moarcframework/views.py
moarcframework/helpers/__init__.py
moarcframework/helpers/auth.py
moarcframework/helpers/paginator.py
moarcframework/http/__init__.py
moarcframework/http/decorators.py
moarcframework/http/generic_serializer.py
moarcframework/http/http.py
moarcframework/management/__init__.py
moarcframework/management/commands/__init__.py
moarcframework/management/commands/clean_migrations.py
moarcframework/management/commands/refresh_template.py
moarcframework/middleware/__init__.py
moarcframework/middleware/thread_local_user_middleware.py
moarcframework/migrations/0001_initial.py
moarcframework/migrations/0002_menu_permission.py
moarcframework/migrations/__init__.py
moarcframework/orm/__init__.py
moarcframework/orm/base_model.py
moarcframework/orm/fields.py
moarcframework/templatetags/__init__.py
moarcframework/templatetags/custom_tags.py
moarcframework/ui/__init__.py
moarcframework/ui/form.html
moarcframework/ui/import.html
moarcframework/ui/table.html
moarc_framework-0.9.dist-info/LICENSE
moarc_framework-0.9.dist-info/METADATA
moarc_framework-0.9.dist-info/WHEEL
moarc_framework-0.9.dist-info/top_level.txt
moarc_framework-0.9.dist-info/RECORD
